dashkit/__init__.py
dashkit-0.0.1.dist-info/licenses/LICENSE
dashkit-0.0.1.dist-info/METADATA
dashkit-0.0.1.dist-info/WHEEL
dashkit-0.0.1.dist-info/top_level.txt
dashkit-0.0.1.dist-info/RECORD
