Metadata-Version: 2.4
Name: dashkit
Version: 0.0.1
Summary: Modern, ready-to-use CSS styles for Flask/Django dashboards
Author: DashKit
License: MIT
Classifier: Framework :: Flask
Classifier: License :: OSI Approved :: MIT License
Classifier: Programming Language :: Python :: 3
Classifier: Topic :: Software Development :: User Interfaces
Classifier: Operating System :: OS Independent
License-File: LICENSE
Provides-Extra: driveui
Requires-Dist: driveui>=0.0.0; extra == "driveui"
Dynamic: author
Dynamic: classifier
Dynamic: description
Dynamic: description-content-type
Dynamic: license
Dynamic: license-file
Dynamic: provides-extra
Dynamic: summary
